[ {
  "categorization" : {
    "tags" : [ ]
  },
  "state" : "SAVED",
  "name" : "bt_panorama_pds_seed",
  "intent_name" : "bt_panorama_pds",
  "scope" : "SEED",
  "data" : [ {
    "id" : "57d3be73-ae80-4a03-b9bd-c0cc64ea0b30",
    "type" : "TRIGGER",
    "source" : "variant",
    "trigger_sentence" : "Hi i'm looking for the bt panorama pds",
    "tags" : [ "nid_05-2021" ]
  }, {
    "id" : "176ebcf4-34ae-485c-bd4d-24db673a12c9",
    "type" : "TRIGGER",
    "source" : "variant",
    "trigger_sentence" : "How do i find the pds",
    "tags" : [ "nid_05-2021" ]
  }, {
    "id" : "81c57684-8893-4171-98e1-5d3f40459adb",
    "type" : "TRIGGER",
    "source" : "variant",
    "trigger_sentence" : "Hi i'm looking for the bt panorama pds",
    "tags" : [ "nid_05-2021" ]
  }, {
    "id" : "12e5bc41-656e-4873-9ea7-6254d0df2304",
    "type" : "TRIGGER",
    "source" : "variant",
    "trigger_sentence" : "How do i find the pds",
    "tags" : [ "nid_05-2021" ]
  }, {
    "id" : "81a95ad4-2c5c-4e5e-a9ee-5deec9d03fd5",
    "type" : "TRIGGER",
    "source" : "variant",
    "trigger_sentence" : "Where are the pds",
    "tags" : [ "nid_05-2021" ]
  }, {
    "id" : "55547dd4-47ae-43c9-a4a3-f5ef7e6f36ba",
    "type" : "TRIGGER",
    "source" : "variant",
    "trigger_sentence" : "Where can i find pds for panorama super full menu",
    "tags" : [ "nid_05-2021" ]
  }, {
    "id" : "4d3a05de-f142-46f9-a8a4-1fa11220be2c",
    "type" : "TRIGGER",
    "source" : "variant",
    "trigger_sentence" : "Where can i locate the pds",
    "tags" : [ "nid_05-2021" ]
  }, {
    "id" : "4ed3cd47-fe27-424e-85ac-a4077d3de354",
    "type" : "TRIGGER",
    "source" : "variant",
    "trigger_sentence" : "Where is pds",
    "tags" : [ "nid_05-2021" ]
  }, {
    "id" : "458838ed-01aa-46d1-9b80-f9f83083256e",
    "type" : "TRIGGER",
    "source" : "variant",
    "trigger_sentence" : "Where is super pds",
    "tags" : [ "nid_05-2021" ]
  }, {
    "id" : "4f02f530-02a8-4689-9608-5f30c60a3604",
    "type" : "TRIGGER",
    "source" : "variant",
    "trigger_sentence" : "Hi im looking for the bt panorama pds",
    "tags" : [ "nid_05-2021" ]
  } ]
} ]