[ {
  "id" : "d095de6f-df48-4e7a-8bbb-413e4499f7a9",
  "active" : true,
  "scope" : "seed",
  "source" : "variant",
  "type" : "TRIGGER",
  "trigger_sentence" : "How do I specify my retirement goals?",
  "intent_name" : "bt_financialplanupdate",
  "updated_date" : "2020-01-13T22:07:41",
  "created_date" : "2020-01-13T22:07:41"
}, {
  "id" : "7206fe2a-ee76-4e61-b799-4bc35e25b6cc",
  "active" : true,
  "scope" : "seed",
  "source" : "variant",
  "tags" : [ "happy" ],
  "type" : "TRIGGER",
  "trigger_sentence" : "how do i set my retirement plans",
  "intent_name" : "bt_financialplanupdate",
  "updated_date" : "2020-01-13T22:08:06",
  "created_date" : "2020-01-13T22:08:06"
}, {
  "id" : "b8e1f0aa-52da-45d5-84f5-6ec507b022c1",
  "active" : true,
  "scope" : "seed",
  "source" : "variant",
  "type" : "TRIGGER",
  "trigger_sentence" : "i want to setup a financial plan",
  "intent_name" : "bt_financialplanupdate",
  "updated_date" : "2020-01-13T22:07:41",
  "created_date" : "2020-01-13T22:07:41"
}, {
  "id" : "31352300-0750-43c8-bb11-7182fb20ed97",
  "active" : true,
  "scope" : "seed",
  "source" : "variant",
  "tags" : [ "happy" ],
  "type" : "TRIGGER",
  "trigger_sentence" : "can i change my goals",
  "intent_name" : "bt_financialplanupdate",
  "updated_date" : "2020-01-13T22:08:06",
  "created_date" : "2020-01-13T22:08:06"
}, {
  "id" : "8a25def9-7717-4a76-9672-fd5d570e7aca",
  "active" : true,
  "scope" : "seed",
  "source" : "variant",
  "type" : "TRIGGER",
  "trigger_sentence" : "I want to create goals",
  "intent_name" : "bt_financialplanupdate",
  "updated_date" : "2020-01-13T22:07:41",
  "created_date" : "2020-01-13T22:07:41"
}, {
  "id" : "90fcbd28-8afb-4b4b-ae92-cc4fbfcf8e1e",
  "active" : true,
  "scope" : "seed",
  "source" : "variant",
  "type" : "TRIGGER",
  "trigger_sentence" : "i want to set investment objectives",
  "intent_name" : "bt_financialplanupdate",
  "updated_date" : "2020-01-13T22:08:06",
  "created_date" : "2020-01-13T22:08:06"
}, {
  "id" : "791592f4-581a-4203-a540-9360825a36ea",
  "active" : true,
  "scope" : "seed",
  "source" : "variant",
  "type" : "TRIGGER",
  "trigger_sentence" : "How do I set my retirement objectives?",
  "intent_name" : "bt_financialplanupdate",
  "updated_date" : "2020-01-13T22:07:41",
  "created_date" : "2020-01-13T22:07:41"
}, {
  "id" : "4688858e-e041-4847-ae79-0a39e5d44324",
  "active" : true,
  "scope" : "seed",
  "source" : "variant",
  "tags" : [ "happy" ],
  "type" : "TRIGGER",
  "trigger_sentence" : "How do I create my financial goals?",
  "intent_name" : "bt_financialplanupdate",
  "updated_date" : "2020-01-13T22:08:06",
  "created_date" : "2020-01-13T22:08:06"
}, {
  "id" : "2081ab09-fd0b-4c92-955f-720c669c9ed4",
  "active" : true,
  "scope" : "seed",
  "source" : "variant",
  "tags" : [ "happy" ],
  "type" : "TRIGGER",
  "trigger_sentence" : "how do i specify my financial plan",
  "intent_name" : "bt_financialplanupdate",
  "updated_date" : "2020-01-13T22:08:06",
  "created_date" : "2020-01-13T22:08:06"
}, {
  "id" : "7c4c6408-6dd7-4dcc-a637-cd732e5e3d3a",
  "active" : true,
  "scope" : "seed",
  "source" : "variant",
  "tags" : [ "happy" ],
  "type" : "TRIGGER",
  "trigger_sentence" : "how do i define my retirement plans",
  "intent_name" : "bt_financialplanupdate",
  "updated_date" : "2020-01-13T22:08:06",
  "created_date" : "2020-01-13T22:08:06"
}, {
  "id" : "ca13ad3e-b430-483f-9cb9-3d59ea5bb08d",
  "active" : true,
  "scope" : "seed",
  "source" : "variant",
  "tags" : [ "happy" ],
  "type" : "TRIGGER",
  "trigger_sentence" : "i want to start saving for my kids' education",
  "intent_name" : "bt_financialplanupdate",
  "updated_date" : "2020-01-13T22:08:06",
  "created_date" : "2020-01-13T22:08:06"
}, {
  "id" : "001c45c5-5803-443a-91cb-f81c0b1f7b3e",
  "active" : true,
  "scope" : "seed",
  "source" : "variant",
  "tags" : [ "happy" ],
  "type" : "TRIGGER",
  "trigger_sentence" : "how do i update my retirement plans",
  "intent_name" : "bt_financialplanupdate",
  "updated_date" : "2020-01-13T22:08:06",
  "created_date" : "2020-01-13T22:08:06"
}, {
  "id" : "0b01497b-3aff-492d-91db-eb5ecf16d9cf",
  "active" : true,
  "scope" : "seed",
  "source" : "variant",
  "tags" : [ "happy" ],
  "type" : "TRIGGER",
  "trigger_sentence" : "Wait I want go back",
  "intent_name" : "bt_financialplanupdate",
  "updated_date" : "2020-01-13T22:08:06",
  "created_date" : "2020-01-13T22:08:06"
}, {
  "id" : "ae1840f7-d4fd-4663-846c-a78ba6fb993e",
  "active" : true,
  "scope" : "seed",
  "source" : "variant",
  "tags" : [ "happy" ],
  "type" : "TRIGGER",
  "trigger_sentence" : "i am no longer saving for college",
  "intent_name" : "bt_financialplanupdate",
  "updated_date" : "2020-01-13T22:08:06",
  "created_date" : "2020-01-13T22:08:06"
}, {
  "id" : "c87e1fb2-fce3-44b9-ad57-5c105ee8222e",
  "active" : true,
  "scope" : "seed",
  "source" : "variant",
  "tags" : [ "happy" ],
  "type" : "TRIGGER",
  "trigger_sentence" : "how do i set my financial objectives",
  "intent_name" : "bt_financialplanupdate",
  "updated_date" : "2020-01-13T22:08:06",
  "created_date" : "2020-01-13T22:08:06"
}, {
  "id" : "e69c3ac4-5da0-4b85-829a-49610e0b3a00",
  "active" : true,
  "scope" : "seed",
  "source" : "variant",
  "type" : "TRIGGER",
  "trigger_sentence" : "How do I define my retirement objectives?",
  "intent_name" : "bt_financialplanupdate",
  "updated_date" : "2020-01-13T22:07:41",
  "created_date" : "2020-01-13T22:07:41"
}, {
  "id" : "aca2cbc9-5422-4371-8d58-118ec88619e4",
  "active" : true,
  "scope" : "seed",
  "source" : "variant",
  "tags" : [ "happy" ],
  "type" : "TRIGGER",
  "trigger_sentence" : "How do I set my financial objectives?",
  "intent_name" : "bt_financialplanupdate",
  "updated_date" : "2020-01-13T22:08:06",
  "created_date" : "2020-01-13T22:08:06"
}, {
  "id" : "fdce8856-a2e3-4ad5-8655-6d7b5aadc7f4",
  "active" : true,
  "scope" : "seed",
  "source" : "variant",
  "tags" : [ "happy" ],
  "type" : "TRIGGER",
  "trigger_sentence" : "How do I specify my financial goals?",
  "intent_name" : "bt_financialplanupdate",
  "updated_date" : "2020-01-13T22:08:06",
  "created_date" : "2020-01-13T22:08:06"
}, {
  "id" : "99c4fde5-3154-469e-9738-44ad316d4f3b",
  "active" : true,
  "scope" : "seed",
  "source" : "variant",
  "tags" : [ "happy" ],
  "type" : "TRIGGER",
  "trigger_sentence" : "how do i create my financial plans",
  "intent_name" : "bt_financialplanupdate",
  "updated_date" : "2020-01-13T22:08:06",
  "created_date" : "2020-01-13T22:08:06"
}, {
  "id" : "418aa72b-3eed-45a3-9400-1fb11014abf1",
  "active" : true,
  "scope" : "seed",
  "source" : "variant",
  "tags" : [ "happy" ],
  "type" : "TRIGGER",
  "trigger_sentence" : "How do I set my retirement goals?",
  "intent_name" : "bt_financialplanupdate",
  "updated_date" : "2020-01-13T22:08:06",
  "created_date" : "2020-01-13T22:08:06"
}, {
  "id" : "b040a05c-9e4e-4ca5-81a7-bbbddaf3cddd",
  "active" : true,
  "scope" : "seed",
  "source" : "variant",
  "tags" : [ "happy" ],
  "type" : "TRIGGER",
  "trigger_sentence" : "how do i set my financial goals",
  "intent_name" : "bt_financialplanupdate",
  "updated_date" : "2020-01-13T22:08:06",
  "created_date" : "2020-01-13T22:08:06"
}, {
  "id" : "c57eec9c-2690-4906-bc61-8471d88f6fa0",
  "active" : true,
  "scope" : "seed",
  "source" : "variant",
  "tags" : [ "happy" ],
  "type" : "TRIGGER",
  "trigger_sentence" : "can my goals be changed",
  "intent_name" : "bt_financialplanupdate",
  "updated_date" : "2020-01-13T22:08:06",
  "created_date" : "2020-01-13T22:08:06"
}, {
  "id" : "ca91faaf-2372-4c3b-963f-e9848440c5cc",
  "active" : true,
  "scope" : "seed",
  "source" : "variant",
  "tags" : [ "happy" ],
  "type" : "TRIGGER",
  "trigger_sentence" : "I want to set some goals up for retirement",
  "intent_name" : "bt_financialplanupdate",
  "updated_date" : "2020-01-13T22:08:06",
  "created_date" : "2020-01-13T22:08:06"
}, {
  "id" : "1409d015-1494-4a2d-83cf-086784a29bf6",
  "active" : true,
  "scope" : "seed",
  "source" : "variant",
  "type" : "TRIGGER",
  "trigger_sentence" : "How do I specify my retirement objectives?",
  "intent_name" : "bt_financialplanupdate",
  "updated_date" : "2020-01-13T22:07:41",
  "created_date" : "2020-01-13T22:07:41"
}, {
  "id" : "3812a1ad-24d8-4ff9-a2e1-b60d9e5d0ff8",
  "active" : true,
  "scope" : "seed",
  "source" : "variant",
  "tags" : [ "happy" ],
  "type" : "TRIGGER",
  "trigger_sentence" : "inquiry about goals",
  "intent_name" : "bt_financialplanupdate",
  "updated_date" : "2020-01-13T22:08:06",
  "created_date" : "2020-01-13T22:08:06"
}, {
  "id" : "1ffeb23c-01b5-4ff3-ace6-94fff4320dbf",
  "active" : true,
  "scope" : "seed",
  "source" : "variant",
  "tags" : [ "happy" ],
  "type" : "TRIGGER",
  "trigger_sentence" : "how do i update my retirement goals",
  "intent_name" : "bt_financialplanupdate",
  "updated_date" : "2020-01-13T22:08:06",
  "created_date" : "2020-01-13T22:08:06"
}, {
  "id" : "e9c864ec-5697-4b2a-8d96-b154acd5af96",
  "active" : true,
  "scope" : "seed",
  "source" : "variant",
  "tags" : [ "happy" ],
  "type" : "TRIGGER",
  "trigger_sentence" : "can i setup financial goals?",
  "intent_name" : "bt_financialplanupdate",
  "updated_date" : "2020-01-13T22:08:06",
  "created_date" : "2020-01-13T22:08:06"
}, {
  "id" : "6572b25b-f8c5-4ff0-9e49-94a18453b935",
  "active" : true,
  "scope" : "seed",
  "source" : "variant",
  "tags" : [ "happy" ],
  "type" : "TRIGGER",
  "trigger_sentence" : "how do i create my retirement plan",
  "intent_name" : "bt_financialplanupdate",
  "updated_date" : "2020-01-13T22:08:06",
  "created_date" : "2020-01-13T22:08:06"
}, {
  "id" : "bdd22c45-1582-44f6-992d-52cb6d5908b7",
  "active" : true,
  "scope" : "seed",
  "source" : "variant",
  "tags" : [ "happy" ],
  "type" : "TRIGGER",
  "trigger_sentence" : "I want to change that",
  "intent_name" : "bt_financialplanupdate",
  "updated_date" : "2020-01-13T22:08:06",
  "created_date" : "2020-01-13T22:08:06"
}, {
  "id" : "78dcbd28-8afb-4b4b-ae92-cc4fbfcf8e1e",
  "active" : true,
  "scope" : "seed",
  "source" : "variant",
  "type" : "TRIGGER",
  "trigger_sentence" : "I want to update my goals",
  "intent_name" : "bt_financialplanupdate",
  "updated_date" : "2020-01-13T22:08:06",
  "created_date" : "2020-01-13T22:08:06"
}, {
  "id" : "e4b44fab-b93c-4497-9cea-7c94d19e2d33",
  "active" : true,
  "scope" : "seed",
  "source" : "variant",
  "type" : "TRIGGER",
  "trigger_sentence" : "How do I create my financial plan?",
  "intent_name" : "bt_financialplanupdate",
  "updated_date" : "2020-01-13T22:07:41",
  "created_date" : "2020-01-13T22:07:41"
}, {
  "id" : "226da853-cac5-4da3-b4c8-49f5b41e285a",
  "active" : true,
  "scope" : "seed",
  "source" : "variant",
  "tags" : [ "happy" ],
  "type" : "TRIGGER",
  "trigger_sentence" : "how do i go about changing my financial goals",
  "intent_name" : "bt_financialplanupdate",
  "updated_date" : "2020-01-13T22:08:06",
  "created_date" : "2020-01-13T22:08:06"
}, {
  "id" : "21a2f07e-7c03-4490-b764-6584a5207d32",
  "active" : true,
  "scope" : "seed",
  "source" : "variant",
  "tags" : [ "happy" ],
  "type" : "TRIGGER",
  "trigger_sentence" : "Edit my last response in my financial goals?",
  "intent_name" : "bt_financialplanupdate",
  "updated_date" : "2020-01-13T22:08:06",
  "created_date" : "2020-01-13T22:08:06"
}, {
  "id" : "5a018d67-5b6b-4a58-900b-a111d2f069d7",
  "active" : true,
  "scope" : "seed",
  "source" : "variant",
  "type" : "TRIGGER",
  "trigger_sentence" : "How do I set my retirement goals?",
  "intent_name" : "bt_financialplanupdate",
  "updated_date" : "2020-01-13T22:07:41",
  "created_date" : "2020-01-13T22:07:41"
}, {
  "id" : "77c3a8ad-3838-4410-bf3b-86ac4b6e1295",
  "active" : true,
  "scope" : "seed",
  "source" : "variant",
  "type" : "TRIGGER",
  "trigger_sentence" : "I want to set some goals up for retirement",
  "intent_name" : "bt_financialplanupdate",
  "updated_date" : "2020-01-13T22:07:41",
  "created_date" : "2020-01-13T22:07:41"
}, {
  "id" : "0bc88a2f-a2e0-4d9d-b2e3-e8a4fde29914",
  "active" : true,
  "scope" : "seed",
  "source" : "variant",
  "tags" : [ "happy" ],
  "type" : "TRIGGER",
  "trigger_sentence" : "i am not interested in buying a home anymore",
  "intent_name" : "bt_financialplanupdate",
  "updated_date" : "2020-01-13T22:08:06",
  "created_date" : "2020-01-13T22:08:06"
}, {
  "id" : "625a0241-ae66-44b6-98f7-429654bdd88a",
  "active" : true,
  "scope" : "seed",
  "source" : "variant",
  "tags" : [ "happy" ],
  "type" : "TRIGGER",
  "trigger_sentence" : "How do I define my retirement plan?",
  "intent_name" : "bt_financialplanupdate",
  "updated_date" : "2020-01-13T22:08:06",
  "created_date" : "2020-01-13T22:08:06"
}, {
  "id" : "0f99c055-7f92-44ab-8d5e-8fa7684085e0",
  "active" : true,
  "scope" : "seed",
  "source" : "variant",
  "tags" : [ "happy" ],
  "type" : "TRIGGER",
  "trigger_sentence" : "How do I specify my retirement plan?",
  "intent_name" : "bt_financialplanupdate",
  "updated_date" : "2020-01-13T22:08:06",
  "created_date" : "2020-01-13T22:08:06"
}, {
  "id" : "8e43e864-dde6-4789-8b50-90d52ac61d3a",
  "active" : true,
  "scope" : "seed",
  "source" : "variant",
  "tags" : [ "happy" ],
  "type" : "TRIGGER",
  "trigger_sentence" : "how do i create my retirement plans",
  "intent_name" : "bt_financialplanupdate",
  "updated_date" : "2020-01-13T22:08:06",
  "created_date" : "2020-01-13T22:08:06"
}, {
  "id" : "a75e0e95-d4ce-4434-89d9-a1aeb001ed87",
  "active" : true,
  "scope" : "seed",
  "source" : "variant",
  "tags" : [ "happy" ],
  "type" : "TRIGGER",
  "trigger_sentence" : "how do i create my financial goals",
  "intent_name" : "bt_financialplanupdate",
  "updated_date" : "2020-01-13T22:08:06",
  "created_date" : "2020-01-13T22:08:06"
}, {
  "id" : "c0a1364a-8fbb-4f05-93fe-fd0ffdf32a4d",
  "active" : true,
  "scope" : "seed",
  "source" : "variant",
  "type" : "TRIGGER",
  "trigger_sentence" : "How do I define my retirement goals?",
  "intent_name" : "bt_financialplanupdate",
  "updated_date" : "2020-01-13T22:07:41",
  "created_date" : "2020-01-13T22:07:41"
}, {
  "id" : "fd839ad5-728f-421e-927e-c8c6e9f314d4",
  "active" : true,
  "scope" : "seed",
  "source" : "variant",
  "tags" : [ "happy" ],
  "type" : "TRIGGER",
  "trigger_sentence" : "i have a child now and would like to set up some financial goals to cover education costs",
  "intent_name" : "bt_financialplanupdate",
  "updated_date" : "2020-01-13T22:08:06",
  "created_date" : "2020-01-13T22:08:06"
}, {
  "id" : "4300e2ce-d66e-4a90-8c45-3865f0c65b61",
  "active" : true,
  "scope" : "seed",
  "source" : "variant",
  "tags" : [ "happy" ],
  "type" : "TRIGGER",
  "trigger_sentence" : "how do i set my financial plan",
  "intent_name" : "bt_financialplanupdate",
  "updated_date" : "2020-01-13T22:08:06",
  "created_date" : "2020-01-13T22:08:06"
}, {
  "id" : "fd18a6aa-ab8d-4f02-b1d6-dbf0d7318ab2",
  "active" : true,
  "scope" : "seed",
  "source" : "variant",
  "tags" : [ "happy" ],
  "type" : "TRIGGER",
  "trigger_sentence" : "How do I define my financial goals?",
  "intent_name" : "bt_financialplanupdate",
  "updated_date" : "2020-01-13T22:08:06",
  "created_date" : "2020-01-13T22:08:06"
}, {
  "id" : "19b80219-420a-4534-914f-53336d6b517a",
  "active" : true,
  "scope" : "seed",
  "source" : "variant",
  "tags" : [ "happy" ],
  "type" : "TRIGGER",
  "trigger_sentence" : "i'd like to change a life goal",
  "intent_name" : "bt_financialplanupdate",
  "updated_date" : "2020-01-13T22:08:06",
  "created_date" : "2020-01-13T22:08:06"
}, {
  "id" : "4887c213-b0c6-4a72-ae16-cda48c5c6292",
  "active" : true,
  "scope" : "seed",
  "source" : "variant",
  "tags" : [ "happy" ],
  "type" : "TRIGGER",
  "trigger_sentence" : "how do i specify my financial plans",
  "intent_name" : "bt_financialplanupdate",
  "updated_date" : "2020-01-13T22:08:06",
  "created_date" : "2020-01-13T22:08:06"
}, {
  "id" : "42b390ff-7c98-45e5-8fad-26e8312a0ede",
  "active" : true,
  "scope" : "seed",
  "source" : "variant",
  "type" : "TRIGGER",
  "trigger_sentence" : "How do I set my financial plan?",
  "intent_name" : "bt_financialplanupdate",
  "updated_date" : "2020-01-13T22:07:41",
  "created_date" : "2020-01-13T22:07:41"
}, {
  "id" : "e2975423-a70d-42a6-b8be-270d07d34130",
  "active" : true,
  "scope" : "seed",
  "source" : "variant",
  "tags" : [ "happy" ],
  "type" : "TRIGGER",
  "trigger_sentence" : "how do i specify my retirement goals",
  "intent_name" : "bt_financialplanupdate",
  "updated_date" : "2020-01-13T22:08:06",
  "created_date" : "2020-01-13T22:08:06"
}, {
  "id" : "b30371a1-81e6-4bbd-920c-14553c6f281f",
  "active" : true,
  "scope" : "seed",
  "source" : "variant",
  "tags" : [ "happy" ],
  "type" : "TRIGGER",
  "trigger_sentence" : "How do I set my financial goals?",
  "intent_name" : "bt_financialplanupdate",
  "updated_date" : "2020-01-13T22:08:06",
  "created_date" : "2020-01-13T22:08:06"
}, {
  "id" : "107817ee-da12-439b-9097-ce4be0d92a16",
  "active" : true,
  "scope" : "seed",
  "source" : "variant",
  "tags" : [ "happy" ],
  "type" : "TRIGGER",
  "trigger_sentence" : "How do I specify my retirement goals?",
  "intent_name" : "bt_financialplanupdate",
  "updated_date" : "2020-01-13T22:08:06",
  "created_date" : "2020-01-13T22:08:06"
}, {
  "id" : "e546d480-f616-47c3-8543-bde8a84bfabf",
  "active" : true,
  "scope" : "seed",
  "source" : "variant",
  "tags" : [ "happy" ],
  "type" : "TRIGGER",
  "trigger_sentence" : "how do i define my retirement goals",
  "intent_name" : "bt_financialplanupdate",
  "updated_date" : "2020-01-13T22:08:06",
  "created_date" : "2020-01-13T22:08:06"
}, {
  "id" : "4cd5de61-5d36-4c2b-8b46-966754a4aade",
  "active" : true,
  "scope" : "seed",
  "source" : "variant",
  "type" : "TRIGGER",
  "trigger_sentence" : "How do I create my financial objectives?",
  "intent_name" : "bt_financialplanupdate",
  "updated_date" : "2020-01-13T22:07:41",
  "created_date" : "2020-01-13T22:07:41"
}, {
  "id" : "6d8f3184-b566-4623-a08f-cad279bf7666",
  "active" : true,
  "scope" : "seed",
  "source" : "variant",
  "tags" : [ "happy" ],
  "type" : "TRIGGER",
  "trigger_sentence" : "How do I define my financial objectives?",
  "intent_name" : "bt_financialplanupdate",
  "updated_date" : "2020-01-13T22:08:06",
  "created_date" : "2020-01-13T22:08:06"
}, {
  "id" : "d82ad260-b323-433b-9872-126cf3072b2c",
  "active" : true,
  "scope" : "seed",
  "source" : "variant",
  "tags" : [ "happy" ],
  "type" : "TRIGGER",
  "trigger_sentence" : "how do i define my financial plan",
  "intent_name" : "bt_financialplanupdate",
  "updated_date" : "2020-01-13T22:08:06",
  "created_date" : "2020-01-13T22:08:06"
}, {
  "id" : "34d83bf8-5b7f-4bdf-a432-38632faf781b",
  "active" : true,
  "scope" : "seed",
  "source" : "variant",
  "tags" : [ "happy" ],
  "type" : "TRIGGER",
  "trigger_sentence" : "how do i set my financial plans",
  "intent_name" : "bt_financialplanupdate",
  "updated_date" : "2020-01-13T22:08:06",
  "created_date" : "2020-01-13T22:08:06"
}, {
  "id" : "41885a1b-fab8-44d4-a112-14027d4d02a7",
  "active" : true,
  "scope" : "seed",
  "source" : "variant",
  "type" : "TRIGGER",
  "trigger_sentence" : "I want to update my goals",
  "intent_name" : "bt_financialplanupdate",
  "updated_date" : "2020-01-13T22:07:41",
  "created_date" : "2020-01-13T22:07:41"
}, {
  "id" : "bdc6f769-342e-451b-8475-b9b96162ae05",
  "active" : true,
  "scope" : "seed",
  "source" : "variant",
  "tags" : [ "happy" ],
  "type" : "TRIGGER",
  "trigger_sentence" : "how do i update my financial plans",
  "intent_name" : "bt_financialplanupdate",
  "updated_date" : "2020-01-13T22:08:06",
  "created_date" : "2020-01-13T22:08:06"
}, {
  "id" : "c51ff35d-4bc0-4602-908f-ce57cd19983d",
  "active" : true,
  "scope" : "seed",
  "source" : "variant",
  "tags" : [ "happy" ],
  "type" : "TRIGGER",
  "trigger_sentence" : "How do I create my financial objectives?",
  "intent_name" : "bt_financialplanupdate",
  "updated_date" : "2020-01-13T22:08:06",
  "created_date" : "2020-01-13T22:08:06"
}, {
  "id" : "b736eaaf-5b92-4a72-9c37-fd951d5183dc",
  "active" : true,
  "scope" : "seed",
  "source" : "variant",
  "type" : "TRIGGER",
  "trigger_sentence" : "How do I create my retirement plan?",
  "intent_name" : "bt_financialplanupdate",
  "updated_date" : "2020-01-13T22:07:41",
  "created_date" : "2020-01-13T22:07:41"
}, {
  "id" : "b049f504-70e2-4e3e-810d-8a8ebe435b05",
  "active" : true,
  "scope" : "seed",
  "source" : "variant",
  "tags" : [ "happy" ],
  "type" : "TRIGGER",
  "trigger_sentence" : "how do i specify my retirement objectives",
  "intent_name" : "bt_financialplanupdate",
  "updated_date" : "2020-01-13T22:08:06",
  "created_date" : "2020-01-13T22:08:06"
}, {
  "id" : "d57f2623-ce23-44b2-ad91-a579e2653e99",
  "active" : true,
  "scope" : "seed",
  "source" : "variant",
  "tags" : [ "happy" ],
  "type" : "TRIGGER",
  "trigger_sentence" : "Can you help me setup goals",
  "intent_name" : "bt_financialplanupdate",
  "updated_date" : "2020-01-13T22:08:06",
  "created_date" : "2020-01-13T22:08:06"
}, {
  "id" : "4d254b58-5b3a-48b9-adda-5ecef3bbe754",
  "active" : true,
  "scope" : "seed",
  "source" : "variant",
  "tags" : [ "happy" ],
  "type" : "TRIGGER",
  "trigger_sentence" : "how do i set my retirement objectives",
  "intent_name" : "bt_financialplanupdate",
  "updated_date" : "2020-01-13T22:08:06",
  "created_date" : "2020-01-13T22:08:06"
}, {
  "id" : "3f28cb29-4348-410b-9b9b-c08279f7b45c",
  "active" : true,
  "scope" : "seed",
  "source" : "variant",
  "tags" : [ "happy" ],
  "type" : "TRIGGER",
  "trigger_sentence" : "how do i set my retirement goals",
  "intent_name" : "bt_financialplanupdate",
  "updated_date" : "2020-01-13T22:08:06",
  "created_date" : "2020-01-13T22:08:06"
}, {
  "id" : "6fe822ed-dfa1-4636-bfe1-6257e4a380a5",
  "active" : true,
  "scope" : "seed",
  "source" : "variant",
  "tags" : [ "happy" ],
  "type" : "TRIGGER",
  "trigger_sentence" : "how do i create my retirement goals",
  "intent_name" : "bt_financialplanupdate",
  "updated_date" : "2020-01-13T22:08:06",
  "created_date" : "2020-01-13T22:08:06"
}, {
  "id" : "524b016b-2d7a-497b-bc8d-30750af77481",
  "active" : true,
  "scope" : "seed",
  "source" : "variant",
  "tags" : [ "happy" ],
  "type" : "TRIGGER",
  "trigger_sentence" : "How do I create my retirement plan?",
  "intent_name" : "bt_financialplanupdate",
  "updated_date" : "2020-01-13T22:08:06",
  "created_date" : "2020-01-13T22:08:06"
}, {
  "id" : "7f42410f-568a-438f-8aa9-4df4cdcd823f",
  "active" : true,
  "scope" : "seed",
  "source" : "variant",
  "type" : "TRIGGER",
  "trigger_sentence" : "Edit my last response in my financial goals?",
  "intent_name" : "bt_financialplanupdate",
  "updated_date" : "2020-01-13T22:07:41",
  "created_date" : "2020-01-13T22:07:41"
}, {
  "id" : "17b186e2-6a0e-4af2-ad27-38c86f37e60b",
  "active" : true,
  "scope" : "seed",
  "source" : "variant",
  "type" : "TRIGGER",
  "trigger_sentence" : "how can i change my financial goals?",
  "intent_name" : "bt_financialplanupdate",
  "updated_date" : "2020-01-13T22:07:41",
  "created_date" : "2020-01-13T22:07:41"
}, {
  "id" : "d7b05350-19a3-4723-b7b7-9a3cd972833b",
  "active" : true,
  "scope" : "seed",
  "source" : "variant",
  "tags" : [ "happy" ],
  "type" : "TRIGGER",
  "trigger_sentence" : "How do I create my retirement objectives?",
  "intent_name" : "bt_financialplanupdate",
  "updated_date" : "2020-01-13T22:08:06",
  "created_date" : "2020-01-13T22:08:06"
}, {
  "id" : "247244cb-d963-4f9e-9b44-e0f9bed853f5",
  "active" : true,
  "scope" : "seed",
  "source" : "variant",
  "tags" : [ "happy" ],
  "type" : "TRIGGER",
  "trigger_sentence" : "How do I set my retirement objectives?",
  "intent_name" : "bt_financialplanupdate",
  "updated_date" : "2020-01-13T22:08:06",
  "created_date" : "2020-01-13T22:08:06"
}, {
  "id" : "2f3b14a1-1f7f-493b-b8af-fae93045fc0d",
  "active" : true,
  "scope" : "seed",
  "source" : "variant",
  "type" : "TRIGGER",
  "trigger_sentence" : "Can you help me setup goals",
  "intent_name" : "bt_financialplanupdate",
  "updated_date" : "2020-01-13T22:07:41",
  "created_date" : "2020-01-13T22:07:41"
}, {
  "id" : "30f0bf32-ad03-44c4-a546-03d46263fc7f",
  "active" : true,
  "scope" : "seed",
  "source" : "variant",
  "type" : "TRIGGER",
  "trigger_sentence" : "inquiry about goals",
  "intent_name" : "bt_financialplanupdate",
  "updated_date" : "2020-01-13T22:07:41",
  "created_date" : "2020-01-13T22:07:41"
}, {
  "id" : "2c755ad0-0b4b-43b1-ba8a-c6567317df42",
  "active" : true,
  "scope" : "seed",
  "source" : "variant",
  "tags" : [ "happy" ],
  "type" : "TRIGGER",
  "trigger_sentence" : "can i setup financial goals",
  "intent_name" : "bt_financialplanupdate",
  "updated_date" : "2020-01-13T22:08:06",
  "created_date" : "2020-01-13T22:08:06"
}, {
  "id" : "5b15b453-f018-4a8e-9c5b-b112ef5b5b86",
  "active" : true,
  "scope" : "seed",
  "source" : "variant",
  "tags" : [ "happy" ],
  "type" : "TRIGGER",
  "trigger_sentence" : "how do i define my retirement objectives",
  "intent_name" : "bt_financialplanupdate",
  "updated_date" : "2020-01-13T22:08:06",
  "created_date" : "2020-01-13T22:08:06"
}, {
  "id" : "97ad0dff-8815-4f62-a961-d21c20d73181",
  "active" : true,
  "scope" : "seed",
  "source" : "variant",
  "tags" : [ "happy" ],
  "type" : "TRIGGER",
  "trigger_sentence" : "can you help me with retirement planning",
  "intent_name" : "bt_financialplanupdate",
  "updated_date" : "2020-01-13T22:08:06",
  "created_date" : "2020-01-13T22:08:06"
}, {
  "id" : "25a30135-7399-4477-bd1f-4ee232497003",
  "active" : true,
  "scope" : "seed",
  "source" : "variant",
  "type" : "TRIGGER",
  "trigger_sentence" : "How do I define my retirement plan?",
  "intent_name" : "bt_financialplanupdate",
  "updated_date" : "2020-01-13T22:07:41",
  "created_date" : "2020-01-13T22:07:41"
}, {
  "id" : "8a9c1bd2-31b6-41d6-b3cc-62960ce2e6a7",
  "active" : true,
  "scope" : "seed",
  "source" : "variant",
  "type" : "TRIGGER",
  "trigger_sentence" : "How do I specify my financial objectives?",
  "intent_name" : "bt_financialplanupdate",
  "updated_date" : "2020-01-13T22:07:41",
  "created_date" : "2020-01-13T22:07:41"
}, {
  "id" : "39d05231-abd4-4998-b201-ee8e4c7f4269",
  "active" : true,
  "scope" : "seed",
  "source" : "variant",
  "tags" : [ "happy" ],
  "type" : "TRIGGER",
  "trigger_sentence" : "how do i define my financial goals",
  "intent_name" : "bt_financialplanupdate",
  "updated_date" : "2020-01-13T22:08:06",
  "created_date" : "2020-01-13T22:08:06"
}, {
  "id" : "23f95dd7-37ef-4268-8c88-d6de0fbfc4e9",
  "active" : true,
  "scope" : "seed",
  "source" : "variant",
  "tags" : [ "happy" ],
  "type" : "TRIGGER",
  "trigger_sentence" : "my retirement plans have changed",
  "intent_name" : "bt_financialplanupdate",
  "updated_date" : "2020-01-13T22:08:06",
  "created_date" : "2020-01-13T22:08:06"
}, {
  "id" : "2dbbaa86-95dc-4a0f-8e2a-045fa17b4219",
  "active" : true,
  "scope" : "seed",
  "source" : "variant",
  "tags" : [ "happy" ],
  "type" : "TRIGGER",
  "trigger_sentence" : "how do i define my financial objectives",
  "intent_name" : "bt_financialplanupdate",
  "updated_date" : "2020-01-13T22:08:06",
  "created_date" : "2020-01-13T22:08:06"
}, {
  "id" : "efcfad88-2870-4d1a-8a7b-08a3e0cbfc9e",
  "active" : true,
  "scope" : "seed",
  "source" : "variant",
  "tags" : [ "happy" ],
  "type" : "TRIGGER",
  "trigger_sentence" : "how do i create my financial plan",
  "intent_name" : "bt_financialplanupdate",
  "updated_date" : "2020-01-13T22:08:06",
  "created_date" : "2020-01-13T22:08:06"
}, {
  "id" : "9827a7b0-4299-4941-babf-cdde6db9474f",
  "active" : true,
  "scope" : "seed",
  "source" : "variant",
  "type" : "TRIGGER",
  "trigger_sentence" : "How do I create my financial goals?",
  "intent_name" : "bt_financialplanupdate",
  "updated_date" : "2020-01-13T22:07:41",
  "created_date" : "2020-01-13T22:07:41"
}, {
  "id" : "fcdd17e0-04a5-420e-9c7a-70e954fbc18d",
  "active" : true,
  "scope" : "seed",
  "source" : "variant",
  "tags" : [ "happy" ],
  "type" : "TRIGGER",
  "trigger_sentence" : "i want to make some updates to my retirement goals",
  "intent_name" : "bt_financialplanupdate",
  "updated_date" : "2020-01-13T22:08:06",
  "created_date" : "2020-01-13T22:08:06"
}, {
  "id" : "3dda4e46-ad33-4492-90e3-91b5d6e8607f",
  "active" : true,
  "scope" : "seed",
  "source" : "variant",
  "tags" : [ "happy" ],
  "type" : "TRIGGER",
  "trigger_sentence" : "How do I create my retirement goals?",
  "intent_name" : "bt_financialplanupdate",
  "updated_date" : "2020-01-13T22:08:06",
  "created_date" : "2020-01-13T22:08:06"
}, {
  "id" : "23mcbd28-8afb-4b4b-ae92-cc4fbfcf8e1e",
  "active" : true,
  "scope" : "seed",
  "source" : "variant",
  "type" : "TRIGGER",
  "trigger_sentence" : "i want to check my investment goals",
  "intent_name" : "bt_financialplanupdate",
  "updated_date" : "2020-01-13T22:08:06",
  "created_date" : "2020-01-13T22:08:06"
}, {
  "id" : "4c9cbec6-b584-4523-a88a-4a60827356e7",
  "active" : true,
  "scope" : "seed",
  "source" : "variant",
  "tags" : [ "happy" ],
  "type" : "TRIGGER",
  "trigger_sentence" : "help me with financial planning",
  "intent_name" : "bt_financialplanupdate",
  "updated_date" : "2020-01-13T22:08:06",
  "created_date" : "2020-01-13T22:08:06"
}, {
  "id" : "4ad406bb-80b4-4af7-8a64-9c5fadd77dc0",
  "active" : true,
  "scope" : "seed",
  "source" : "variant",
  "tags" : [ "happy" ],
  "type" : "TRIGGER",
  "trigger_sentence" : "how do i define my financial plans",
  "intent_name" : "bt_financialplanupdate",
  "updated_date" : "2020-01-13T22:08:06",
  "created_date" : "2020-01-13T22:08:06"
}, {
  "id" : "7aeb0fa6-b2a8-400f-a53f-ca81c5c027fd",
  "active" : true,
  "scope" : "seed",
  "source" : "variant",
  "tags" : [ "happy" ],
  "type" : "TRIGGER",
  "trigger_sentence" : "i want to setup a financial plan",
  "intent_name" : "bt_financialplanupdate",
  "updated_date" : "2020-01-13T22:08:06",
  "created_date" : "2020-01-13T22:08:06"
}, {
  "id" : "1901161c-a7c6-4a6f-8a4b-c51216e116c8",
  "active" : true,
  "scope" : "seed",
  "source" : "variant",
  "type" : "TRIGGER",
  "trigger_sentence" : "how can i change my financial goals?",
  "intent_name" : "bt_financialplanupdate",
  "updated_date" : "2020-01-13T22:08:06",
  "created_date" : "2020-01-13T22:08:06"
}, {
  "id" : "89fcbd28-8afb-4b4b-ae92-cc4fbfcf8e1e",
  "active" : true,
  "scope" : "seed",
  "source" : "variant",
  "type" : "TRIGGER",
  "trigger_sentence" : "create a savings goal",
  "intent_name" : "bt_financialplanupdate",
  "updated_date" : "2020-01-13T22:08:06",
  "created_date" : "2020-01-13T22:08:06"
}, {
  "id" : "4e073ff2-5c2a-4605-8695-2d47d0283edd",
  "active" : true,
  "scope" : "seed",
  "source" : "variant",
  "tags" : [ "happy" ],
  "type" : "TRIGGER",
  "trigger_sentence" : "how do i specify my retirement plan",
  "intent_name" : "bt_financialplanupdate",
  "updated_date" : "2020-01-13T22:08:06",
  "created_date" : "2020-01-13T22:08:06"
}, {
  "id" : "b7b21c46-dc7e-4848-ae85-c6818accc579",
  "active" : true,
  "scope" : "seed",
  "source" : "variant",
  "type" : "TRIGGER",
  "trigger_sentence" : "How do I specify my retirement plan?",
  "intent_name" : "bt_financialplanupdate",
  "updated_date" : "2020-01-13T22:07:41",
  "created_date" : "2020-01-13T22:07:41"
}, {
  "id" : "634538f2-b821-401c-b992-f7911857fdfb",
  "active" : true,
  "scope" : "seed",
  "source" : "variant",
  "type" : "TRIGGER",
  "trigger_sentence" : "How do I define my financial goals?",
  "intent_name" : "bt_financialplanupdate",
  "updated_date" : "2020-01-13T22:07:41",
  "created_date" : "2020-01-13T22:07:41"
}, {
  "id" : "8832fc6d-aa46-4fba-97ef-fb57ecbefb6a",
  "active" : true,
  "scope" : "seed",
  "source" : "variant",
  "type" : "TRIGGER",
  "trigger_sentence" : "How do I set my financial goals?",
  "intent_name" : "bt_financialplanupdate",
  "updated_date" : "2020-01-13T22:07:41",
  "created_date" : "2020-01-13T22:07:41"
}, {
  "id" : "ac4288e2-1d6d-4f7d-8ac7-306864947f39",
  "active" : true,
  "scope" : "seed",
  "source" : "variant",
  "tags" : [ "happy" ],
  "type" : "TRIGGER",
  "trigger_sentence" : "How do I define my retirement objectives?",
  "intent_name" : "bt_financialplanupdate",
  "updated_date" : "2020-01-13T22:08:06",
  "created_date" : "2020-01-13T22:08:06"
}, {
  "id" : "46b995d1-87c0-4611-ae16-505436a2f019",
  "active" : true,
  "scope" : "seed",
  "source" : "variant",
  "type" : "TRIGGER",
  "trigger_sentence" : "How do I define my financial objectives?",
  "intent_name" : "bt_financialplanupdate",
  "updated_date" : "2020-01-13T22:07:41",
  "created_date" : "2020-01-13T22:07:41"
}, {
  "id" : "21ab6474-bb55-43d0-9c1c-1ef4adb2e45b",
  "active" : true,
  "scope" : "seed",
  "source" : "variant",
  "type" : "TRIGGER",
  "trigger_sentence" : "help me with financial planning",
  "intent_name" : "bt_financialplanupdate",
  "updated_date" : "2020-01-13T22:07:41",
  "created_date" : "2020-01-13T22:07:41"
}, {
  "id" : "22d4f2f7-5fcd-462e-90be-e77ef4930b12",
  "active" : true,
  "scope" : "seed",
  "source" : "variant",
  "tags" : [ "happy" ],
  "type" : "TRIGGER",
  "trigger_sentence" : "I want to create goals",
  "intent_name" : "bt_financialplanupdate",
  "updated_date" : "2020-01-13T22:08:06",
  "created_date" : "2020-01-13T22:08:06"
}, {
  "id" : "6fbc3444-a978-4305-898a-11402bde3ce9",
  "active" : true,
  "scope" : "seed",
  "source" : "variant",
  "type" : "TRIGGER",
  "trigger_sentence" : "How do I create my retirement goals?",
  "intent_name" : "bt_financialplanupdate",
  "updated_date" : "2020-01-13T22:07:41",
  "created_date" : "2020-01-13T22:07:41"
}, {
  "id" : "e2a6d57b-0b3f-4421-990d-8c7d6a6a2520",
  "active" : true,
  "scope" : "seed",
  "source" : "variant",
  "tags" : [ "happy" ],
  "type" : "TRIGGER",
  "trigger_sentence" : "How do I set my financial plan?",
  "intent_name" : "bt_financialplanupdate",
  "updated_date" : "2020-01-13T22:08:06",
  "created_date" : "2020-01-13T22:08:06"
}, {
  "id" : "0261cbac-4f5c-4e51-aecc-0dc63dc19856",
  "active" : true,
  "scope" : "seed",
  "source" : "variant",
  "type" : "TRIGGER",
  "trigger_sentence" : "How do I create my retirement objectives?",
  "intent_name" : "bt_financialplanupdate",
  "updated_date" : "2020-01-13T22:07:41",
  "created_date" : "2020-01-13T22:07:41"
}, {
  "id" : "a2bc4fda-8e5a-4985-a94b-7d952144e6a5",
  "active" : true,
  "scope" : "seed",
  "source" : "variant",
  "tags" : [ "happy" ],
  "type" : "TRIGGER",
  "trigger_sentence" : "how do i update my retirement objectives",
  "intent_name" : "bt_financialplanupdate",
  "updated_date" : "2020-01-13T22:08:06",
  "created_date" : "2020-01-13T22:08:06"
}, {
  "id" : "2e605e8d-290a-472b-9031-92f280f26f9e",
  "active" : true,
  "scope" : "seed",
  "source" : "variant",
  "tags" : [ "happy" ],
  "type" : "TRIGGER",
  "trigger_sentence" : "Edit my last response",
  "intent_name" : "bt_financialplanupdate",
  "updated_date" : "2020-01-13T22:08:06",
  "created_date" : "2020-01-13T22:08:06"
}, {
  "id" : "16896f40-03de-4ca8-91ed-d0655132ac49",
  "active" : true,
  "scope" : "seed",
  "source" : "variant",
  "tags" : [ "happy" ],
  "type" : "TRIGGER",
  "trigger_sentence" : "How do I define my retirement goals?",
  "intent_name" : "bt_financialplanupdate",
  "updated_date" : "2020-01-13T22:08:06",
  "created_date" : "2020-01-13T22:08:06"
}, {
  "id" : "e526c069-afd1-48af-94da-4a214e121d48",
  "active" : true,
  "scope" : "seed",
  "source" : "variant",
  "tags" : [ "happy" ],
  "type" : "TRIGGER",
  "trigger_sentence" : "how do i specify my financial goals",
  "intent_name" : "bt_financialplanupdate",
  "updated_date" : "2020-01-13T22:08:06",
  "created_date" : "2020-01-13T22:08:06"
}, {
  "id" : "5494bb05-6be4-4733-849f-c41a3092d5d9",
  "active" : true,
  "scope" : "seed",
  "source" : "variant",
  "tags" : [ "happy" ],
  "type" : "TRIGGER",
  "trigger_sentence" : "How do I specify my financial plan?",
  "intent_name" : "bt_financialplanupdate",
  "updated_date" : "2020-01-13T22:08:06",
  "created_date" : "2020-01-13T22:08:06"
}, {
  "id" : "c9701994-145d-4cc1-875d-e61cef339f03",
  "active" : true,
  "scope" : "seed",
  "source" : "variant",
  "tags" : [ "happy" ],
  "type" : "TRIGGER",
  "trigger_sentence" : "i want to plan for another house",
  "intent_name" : "bt_financialplanupdate",
  "updated_date" : "2020-01-13T22:08:06",
  "created_date" : "2020-01-13T22:08:06"
}, {
  "id" : "b70948b2-08c0-4a21-9806-42cb96c16169",
  "active" : true,
  "scope" : "seed",
  "source" : "variant",
  "tags" : [ "happy" ],
  "type" : "TRIGGER",
  "trigger_sentence" : "How do I create my financial plan?",
  "intent_name" : "bt_financialplanupdate",
  "updated_date" : "2020-01-13T22:08:06",
  "created_date" : "2020-01-13T22:08:06"
}, {
  "id" : "26a5bf41-0e88-40c5-aa59-3636dac4a14f",
  "active" : true,
  "scope" : "seed",
  "source" : "variant",
  "tags" : [ "happy" ],
  "type" : "TRIGGER",
  "trigger_sentence" : "how do i specify my financial objectives",
  "intent_name" : "bt_financialplanupdate",
  "updated_date" : "2020-01-13T22:08:06",
  "created_date" : "2020-01-13T22:08:06"
}, {
  "id" : "b9fadef3-1656-47cc-925e-3c688d00382d",
  "active" : true,
  "scope" : "seed",
  "source" : "variant",
  "tags" : [ "happy" ],
  "type" : "TRIGGER",
  "trigger_sentence" : "how do i set my retirement plan",
  "intent_name" : "bt_financialplanupdate",
  "updated_date" : "2020-01-13T22:08:06",
  "created_date" : "2020-01-13T22:08:06"
}, {
  "id" : "7467f55a-c688-4300-bca5-e22787313e35",
  "active" : true,
  "scope" : "seed",
  "source" : "variant",
  "tags" : [ "happy" ],
  "type" : "TRIGGER",
  "trigger_sentence" : "How do I set my retirement plan?",
  "intent_name" : "bt_financialplanupdate",
  "updated_date" : "2020-01-13T22:08:06",
  "created_date" : "2020-01-13T22:08:06"
}, {
  "id" : "72ca7454-e640-4b82-b445-38ef7f93057b",
  "active" : true,
  "scope" : "seed",
  "source" : "variant",
  "tags" : [ "happy" ],
  "type" : "TRIGGER",
  "trigger_sentence" : "how can i change my financial goals",
  "intent_name" : "bt_financialplanupdate",
  "updated_date" : "2020-01-13T22:08:06",
  "created_date" : "2020-01-13T22:08:06"
}, {
  "id" : "2a8649d2-0c2f-4862-b6f9-16f2eb9bab17",
  "active" : true,
  "scope" : "seed",
  "source" : "variant",
  "type" : "TRIGGER",
  "trigger_sentence" : "How do I specify my financial goals?",
  "intent_name" : "bt_financialplanupdate",
  "updated_date" : "2020-01-13T22:07:41",
  "created_date" : "2020-01-13T22:07:41"
}, {
  "id" : "d7bac198-7e23-4a11-a952-301be935c17f",
  "active" : true,
  "scope" : "seed",
  "source" : "variant",
  "type" : "TRIGGER",
  "trigger_sentence" : "How do I set my retirement plan?",
  "intent_name" : "bt_financialplanupdate",
  "updated_date" : "2020-01-13T22:07:41",
  "created_date" : "2020-01-13T22:07:41"
}, {
  "id" : "7706c42f-90f3-4287-99d0-8c15cd8c733d",
  "active" : true,
  "scope" : "seed",
  "source" : "variant",
  "tags" : [ "happy" ],
  "type" : "TRIGGER",
  "trigger_sentence" : "Can you help me with retirement planning?",
  "intent_name" : "bt_financialplanupdate",
  "updated_date" : "2020-01-13T22:08:06",
  "created_date" : "2020-01-13T22:08:06"
}, {
  "id" : "8a725308-dd53-420c-b177-49d3dd318430",
  "active" : true,
  "scope" : "seed",
  "source" : "variant",
  "tags" : [ "happy" ],
  "type" : "TRIGGER",
  "trigger_sentence" : "i need to change my retirement goals",
  "intent_name" : "bt_financialplanupdate",
  "updated_date" : "2020-01-13T22:08:06",
  "created_date" : "2020-01-13T22:08:06"
}, {
  "id" : "ebe3fdbf-f923-4cf7-8a35-4360c1fd45e2",
  "active" : true,
  "scope" : "seed",
  "source" : "variant",
  "tags" : [ "happy" ],
  "type" : "TRIGGER",
  "trigger_sentence" : "i set up my goals but now i want to change them",
  "intent_name" : "bt_financialplanupdate",
  "updated_date" : "2020-01-13T22:08:06",
  "created_date" : "2020-01-13T22:08:06"
}, {
  "id" : "00d80cf2-63e4-440e-8bf1-8a19e77caa6f",
  "active" : true,
  "scope" : "seed",
  "source" : "variant",
  "tags" : [ "happy" ],
  "type" : "TRIGGER",
  "trigger_sentence" : "how do i update my financial objectives",
  "intent_name" : "bt_financialplanupdate",
  "updated_date" : "2020-01-13T22:08:06",
  "created_date" : "2020-01-13T22:08:06"
}, {
  "id" : "566aedd3-9686-4625-856f-6ce259fbafb8",
  "active" : true,
  "scope" : "seed",
  "source" : "variant",
  "tags" : [ "happy" ],
  "type" : "TRIGGER",
  "trigger_sentence" : "How do I specify my financial objectives?",
  "intent_name" : "bt_financialplanupdate",
  "updated_date" : "2020-01-13T22:08:06",
  "created_date" : "2020-01-13T22:08:06"
}, {
  "id" : "e6886b92-328e-46c1-b906-70433be185b2",
  "active" : true,
  "scope" : "seed",
  "source" : "variant",
  "tags" : [ "happy" ],
  "type" : "TRIGGER",
  "trigger_sentence" : "How do I specify my retirement objectives?",
  "intent_name" : "bt_financialplanupdate",
  "updated_date" : "2020-01-13T22:08:06",
  "created_date" : "2020-01-13T22:08:06"
}, {
  "id" : "6c826583-b502-437b-82a9-d7aece1b8f8f",
  "active" : true,
  "scope" : "seed",
  "source" : "variant",
  "tags" : [ "happy" ],
  "type" : "TRIGGER",
  "trigger_sentence" : "how do i create my financial objectives",
  "intent_name" : "bt_financialplanupdate",
  "updated_date" : "2020-01-13T22:08:06",
  "created_date" : "2020-01-13T22:08:06"
}, {
  "id" : "ca2e5833-c79f-45cd-9127-5d66e23e645b",
  "active" : true,
  "scope" : "seed",
  "source" : "variant",
  "tags" : [ "happy" ],
  "type" : "TRIGGER",
  "trigger_sentence" : "i am going to buy a new home, will this affect my goals",
  "intent_name" : "bt_financialplanupdate",
  "updated_date" : "2020-01-13T22:08:06",
  "created_date" : "2020-01-13T22:08:06"
}, {
  "id" : "8a1bfba2-4693-4899-b555-f517d170625b",
  "active" : true,
  "scope" : "seed",
  "source" : "variant",
  "tags" : [ "happy" ],
  "type" : "TRIGGER",
  "trigger_sentence" : "how do i update my financial goals",
  "intent_name" : "bt_financialplanupdate",
  "updated_date" : "2020-01-13T22:08:06",
  "created_date" : "2020-01-13T22:08:06"
}, {
  "id" : "f0be2584-0ffc-41c6-97fd-60257f9df6b6",
  "active" : true,
  "scope" : "seed",
  "source" : "variant",
  "tags" : [ "happy" ],
  "type" : "TRIGGER",
  "trigger_sentence" : "i want to change my financial goals",
  "intent_name" : "bt_financialplanupdate",
  "updated_date" : "2020-01-13T22:08:06",
  "created_date" : "2020-01-13T22:08:06"
}, {
  "id" : "8da42aea-8e72-4635-81d3-0200e28ed3c3",
  "active" : true,
  "scope" : "seed",
  "source" : "variant",
  "tags" : [ "happy" ],
  "type" : "TRIGGER",
  "trigger_sentence" : "how do i specify my retirement plans",
  "intent_name" : "bt_financialplanupdate",
  "updated_date" : "2020-01-13T22:08:06",
  "created_date" : "2020-01-13T22:08:06"
}, {
  "id" : "fe4971c3-7c46-4c32-8f56-a44b51902cc2",
  "active" : true,
  "scope" : "seed",
  "source" : "variant",
  "type" : "TRIGGER",
  "trigger_sentence" : "How do I set my financial objectives?",
  "intent_name" : "bt_financialplanupdate",
  "updated_date" : "2020-01-13T22:07:41",
  "created_date" : "2020-01-13T22:07:41"
}, {
  "id" : "530de6d0-1056-4958-a72b-087c76ce7107",
  "active" : true,
  "scope" : "seed",
  "source" : "variant",
  "type" : "TRIGGER",
  "trigger_sentence" : "Can you help me with retirement planning?",
  "intent_name" : "bt_financialplanupdate",
  "updated_date" : "2020-01-13T22:07:41",
  "created_date" : "2020-01-13T22:07:41"
}, {
  "id" : "7a2d35af-6282-413c-a15c-73b2a1fce41c",
  "active" : true,
  "scope" : "seed",
  "source" : "variant",
  "type" : "TRIGGER",
  "trigger_sentence" : "can i setup financial goals?",
  "intent_name" : "bt_financialplanupdate",
  "updated_date" : "2020-01-13T22:07:41",
  "created_date" : "2020-01-13T22:07:41"
}, {
  "id" : "d8bf9165-7754-4a8c-8a43-8f7aa031fc3a",
  "active" : true,
  "scope" : "seed",
  "source" : "variant",
  "tags" : [ "happy" ],
  "type" : "TRIGGER",
  "trigger_sentence" : "How do I define my financial plan?",
  "intent_name" : "bt_financialplanupdate",
  "updated_date" : "2020-01-13T22:08:06",
  "created_date" : "2020-01-13T22:08:06"
}, {
  "id" : "914935f4-f59a-491b-aa23-d091396ed61e",
  "active" : true,
  "scope" : "seed",
  "source" : "variant",
  "tags" : [ "happy" ],
  "type" : "TRIGGER",
  "trigger_sentence" : "i am going to get a new house, how will this impact my goals",
  "intent_name" : "bt_financialplanupdate",
  "updated_date" : "2020-01-13T22:08:06",
  "created_date" : "2020-01-13T22:08:06"
}, {
  "id" : "846193d4-5e6f-494d-9584-05b12a0fe96d",
  "active" : true,
  "scope" : "seed",
  "source" : "variant",
  "tags" : [ "happy" ],
  "type" : "TRIGGER",
  "trigger_sentence" : "how do i create my retirement objectives",
  "intent_name" : "bt_financialplanupdate",
  "updated_date" : "2020-01-13T22:08:06",
  "created_date" : "2020-01-13T22:08:06"
}, {
  "id" : "8e94876e-4d19-4e7f-b268-8ee9b6634206",
  "active" : true,
  "scope" : "seed",
  "source" : "variant",
  "tags" : [ "happy" ],
  "type" : "TRIGGER",
  "trigger_sentence" : "how do i define my retirement plan",
  "intent_name" : "bt_financialplanupdate",
  "updated_date" : "2020-01-13T22:08:06",
  "created_date" : "2020-01-13T22:08:06"
}, {
  "id" : "2d3cc570-65b6-4a70-b79b-b0c37d052e05",
  "active" : true,
  "scope" : "seed",
  "source" : "variant",
  "type" : "TRIGGER",
  "trigger_sentence" : "How do I define my financial plan?",
  "intent_name" : "bt_financialplanupdate",
  "updated_date" : "2020-01-13T22:07:41",
  "created_date" : "2020-01-13T22:07:41"
}, {
  "id" : "cd3a3b86-a980-49b7-9725-172bee9e79d6",
  "active" : true,
  "scope" : "seed",
  "source" : "variant",
  "type" : "TRIGGER",
  "trigger_sentence" : "How do I specify my financial plan?",
  "intent_name" : "bt_financialplanupdate",
  "updated_date" : "2020-01-13T22:07:41",
  "created_date" : "2020-01-13T22:07:41"
} ]